aa25/__init__.py
aa25/addim.py
aa25/test.py
aa25-0.2.dist-info/LICENSE
aa25-0.2.dist-info/METADATA
aa25-0.2.dist-info/WHEEL
aa25-0.2.dist-info/top_level.txt
aa25-0.2.dist-info/RECORD
