Metadata-Version: 2.1
Name: aa25
Version: 0.2
Summary: add douyin effect to image
Home-page: https://github.com/pythonml/douyin_image
Author: gao
Author-email: 
License-File: LICENSE
